tqma/README.MD
tqma/__init__.py
tqma/requirements.txt
tqma/thirdparty.json
tqma-0.10.dist-info/LICENSE.rst
tqma-0.10.dist-info/METADATA
tqma-0.10.dist-info/WHEEL
tqma-0.10.dist-info/top_level.txt
tqma-0.10.dist-info/RECORD
