Metadata-Version: 2.1
Name: tqma
Version: 0.10
Summary: A poor man's tqdm - no progress bar, only numbers, no configuration options
Home-page: https://github.com/hansalemaos/tqma
Author: Johannes Fischer
Author-email: aulasparticularesdealemaosp@gmail.com
License: MIT
Keywords: tqdm,progress bar
Classifier: Development Status :: 4 - Beta
Classifier: Programming Language :: Python :: 3 :: Only
Classifier: Programming Language :: Python :: 3.10
Classifier: Topic :: Software Development :: Libraries :: Python Modules
Classifier: Topic :: Utilities
License-File: LICENSE.rst
